[
    {
        "name": "OPP Parity",
        "algs": [
            "2R2 U2 2R2 Uw2 2R2 Uw2"
        ]
    },
    {
        "name": "Adj Parity",
        "algs": [
            "R' U R U' 2R2 U2' 2R2 Uw2' 2R2 Uw2' U' R' U' R"
        ]
    },
    {
        "name": "CwO",
        "algs": [
            "M2 U' M2 U' M' U2 M2 U2 M' Parity Alg (2R2)M2 U' M2 U' M' U2 M2 U2 M' 2R2 U2 2R2 Uw2 2R2 Uw2"
        ]
    },
    {
        "name": "CcwO",
        "algs": [
            "Uw2 2L2 Uw2 2L2 U2 3Rw' Rw2 R' U2 M2 U2 M' U M2 U M2"
        ]
    },
    {
        "name": "W",
        "algs": [
            "U' R U' R U R U R U' R' U' R2 Parity Alg (2R2)U' R U' R U R U R U' R' U' R2 2R2 U2 2R2 Uw2 2R2 Uw2"
        ]
    },
    {
        "name": "Pj",
        "algs": [
            "R U R' U' R' F R2 U' R' U' R U R' F' U' 2L2 U2 2L2 Uw2 2L2 Uw2"
        ]
    },
    {
        "name": "Ba",
        "algs": [
            "x' Rw2 U2 Rw2 Uw2 2R2 Uw2 F 3Rw U' R U2 L' U R'"
        ]
    },
    {
        "name": "Bb",
        "algs": [
            "y x Rw2 U2 Rw2 Uw2 2R2 Uw2 B 3Rw' U R' U2 L U' R"
        ]
    },
    {
        "name": "Ca",
        "algs": [
            "y2 Uw2 2R2 Uw2 2R2 U2 Rw2 F R U R U' R' F' R U2 R' U2 R"
        ]
    },
    {
        "name": "Cb",
        "algs": [
            "y R' U2 R U2 R' F R U R' U' R' F' Rw2 U2 2R2 Uw2 2R2 Uw2"
        ]
    },
    {
        "name": "Da",
        "algs": [
            "R' U L' U2 R U' 3Rw B Rw2 U2 Rw2 Uw2 2R2 Uw2 x'"
        ]
    },
    {
        "name": "Db",
        "algs": [
            "R U R' F' R U R' U' R' F R2 U' R' u2 2R2 u2 2R2 U2 2R2"
        ]
    },
    {
        "name": "Ka",
        "algs": [
            "y 3Lw' U R' D2 R U' R' D2 x' Rw2 U2 2R2 Uw2 2R2 Uw2"
        ]
    },
    {
        "name": "Kb",
        "algs": [
            "y' 3Rw U' L D2 L' U L D2 x' Lw2 U2 2L2 Uw2 2L2 Uw2"
        ]
    },
    {
        "name": "M",
        "algs": [
            "R U R' U' R' F R2 U' R' U' R U R' F' Parity Alg (2R2)R U R' U' R' F R2 U' R' U' R U R' F' 2R2 U2 2R2 Uw2 2R2 Uw2"
        ]
    },
    {
        "name": "Pa",
        "algs": [
            "R U R' F' R U R' U' R' F R2 U' R' U' 2R2 U2 2R2 u2 2R2 u2"
        ]
    },
    {
        "name": "Pb",
        "algs": [
            "2R2 U2 2R2 u2 2R2 u2 R U R' F' R U R' U' R' F R2 U' R'"
        ]
    },
    {
        "name": "Diag C",
        "algs": [
            "F R U' R' U' R U R' F' U' 2R2 U2 2R2 u2 2R2 u2 U' R U R' U' R' F R F'"
        ]
    },
    {
        "name": "Q",
        "algs": [
            "z Rw2 Uw2' R2' Uw2' F R U R' U' R U R' U' R U R' U' F' U2' R2 Uw2' Rw2' z'"
        ]
    },
    {
        "name": "Sa",
        "algs": [
            "F R U' R' U' R U R' F' R U R' U' R' F R F' U' 2R2 U2 2R2 u2 2R2 u2"
        ]
    },
    {
        "name": "Sb",
        "algs": [
            "F R U' R' U' R U R' F' R U R' U' R' F R F' Parity Alg (2R2)F R U' R' U' R U R' F' R U R' U' R' F R F' 2R2 U2 2R2 Uw2 2R2 Uw2"
        ]
    },
    {
        "name": "X",
        "algs": [
            "Rw2 F2 U2 Rw2 F' U' R' U R U' R' U R U' R' U R F R2 U2 F2 Rw2"
        ]
    }
]
